odoo/addons/mail_chatter_company_tracking/README.rst
odoo/addons/mail_chatter_company_tracking/__init__.py
odoo/addons/mail_chatter_company_tracking/__manifest__.py
odoo/addons/mail_chatter_company_tracking/i18n/it.po
odoo/addons/mail_chatter_company_tracking/i18n/mail_chatter_company_tracking.pot
odoo/addons/mail_chatter_company_tracking/models/__init__.py
odoo/addons/mail_chatter_company_tracking/models/mail_message.py
odoo/addons/mail_chatter_company_tracking/models/mail_tracking_value.py
odoo/addons/mail_chatter_company_tracking/readme/CONTRIBUTORS.rst
odoo/addons/mail_chatter_company_tracking/readme/DESCRIPTION.rst
odoo/addons/mail_chatter_company_tracking/static/description/icon.png
odoo/addons/mail_chatter_company_tracking/static/description/index.html
odoo/addons/mail_chatter_company_tracking/static/src/components/message/message.xml
odoo/addons/mail_chatter_company_tracking/tests/__init__.py
odoo/addons/mail_chatter_company_tracking/tests/test_mail_tracking.py
odoo14_addon_mail_chatter_company_tracking-14.0.1.0.1.dev6.dist-info/METADATA
odoo14_addon_mail_chatter_company_tracking-14.0.1.0.1.dev6.dist-info/WHEEL
odoo14_addon_mail_chatter_company_tracking-14.0.1.0.1.dev6.dist-info/top_level.txt
odoo14_addon_mail_chatter_company_tracking-14.0.1.0.1.dev6.dist-info/RECORD
