Metadata-Version: 2.1
Name: odoo14-addon-mail_chatter_company_tracking
Version: 14.0.1.0.1.dev6
Summary: This add-on includes the company name in the email chatter tracking when it is a company-dependent field.
Home-page: https://github.com/OCA/social
Author: Binhex, Odoo Community Association (OCA)
Author-email: support@odoo-community.org
License: AGPL-3
Classifier: Programming Language :: Python
Classifier: Framework :: Odoo
Classifier: Framework :: Odoo :: 14.0
Classifier: License :: OSI Approved :: GNU Affero General Public License v3
Requires-Python: >=3.6
Requires-Dist: odoo<14.1dev,>=14.0a
